tests/__init__.py
uniqcharstest5-1.0.dist-info/LICENSE
uniqcharstest5-1.0.dist-info/METADATA
uniqcharstest5-1.0.dist-info/WHEEL
uniqcharstest5-1.0.dist-info/entry_points.txt
uniqcharstest5-1.0.dist-info/top_level.txt
uniqcharstest5-1.0.dist-info/RECORD
